scboa/__init__.py
scboa/cli.py
scboa/pipeline.py
scboa-0.1.7.dist-info/licenses/LICENSE
scboa-0.1.7.dist-info/METADATA
scboa-0.1.7.dist-info/WHEEL
scboa-0.1.7.dist-info/entry_points.txt
scboa-0.1.7.dist-info/top_level.txt
scboa-0.1.7.dist-info/RECORD
