Metadata-Version: 2.4
Name: scboa
Version: 0.1.7
Summary: scBOA: scRNA-seq Bayesian Optimization and Analysis pipeline
Author-email: Qiang Su <su@chemie.uni-siegen.de>
Maintainer-email: Qiang Su <su@chemie.uni-siegen.de>
License: MIT License
Project-URL: Homepage, https://github.com/QiangSu/scBOA
Project-URL: Bug Tracker, https://github.com/QiangSu/scBOA/issues
Project-URL: Source, https://github.com/QiangSu/scBOA
Keywords: single-cell RNA-seq,scRNA-seq,bayesian optimization,bioinformatics,cell type annotation,scanpy
Classifier: Programming Language :: Python :: 3
Classifier: Programming Language :: Python :: 3.8
Classifier: Programming Language :: Python :: 3.9
Classifier: Programming Language :: Python :: 3.10
Classifier: Programming Language :: Python :: 3.11
Classifier: License :: OSI Approved :: MIT License
Classifier: Operating System :: OS Independent
Classifier: Intended Audience :: Science/Research
Classifier: Topic :: Scientific/Engineering :: Bio-Informatics
Requires-Python: >=3.8
License-File: LICENSE
Requires-Dist: scanpy>=1.9.0
Requires-Dist: anndata
Requires-Dist: pandas
Requires-Dist: numpy
Requires-Dist: scipy
Requires-Dist: scikit-learn
Requires-Dist: matplotlib
Requires-Dist: seaborn
Requires-Dist: scikit-optimize
Requires-Dist: celltypist>=1.5.0
Requires-Dist: harmonypy
Requires-Dist: leidenalg
Requires-Dist: python-igraph
Requires-Dist: openpyxl
Dynamic: license-file
